rtms/__init__.py
rtms/__init__.pyi
rtms/_rtms.cpython-311-x86_64-linux-gnu.so
rtms/librtmsdk.so.0
rtms-1.0.2.dist-info/METADATA
rtms-1.0.2.dist-info/WHEEL
rtms-1.0.2.dist-info/RECORD
rtms-1.0.2.dist-info/licenses/LICENSE.md
