Metadata-Version: 2.1
Name: rtms
Version: 1.0.2
Summary: Python bindings for the Zoom RTMS C SDK - Real-Time Media Streaming
Keywords: zoom,rtms,realtime,media,streaming,real-time,sdk
Author: Zoom Communications, Inc.
Maintainer-Email: Max Mansfield <max.mansfield@zoom.us>
License: MIT
Classifier: Development Status :: 3 - Alpha
Classifier: Intended Audience :: Developers
Classifier: License :: OSI Approved :: MIT License
Classifier: Programming Language :: C++
Classifier: Programming Language :: Python :: 3
Classifier: Programming Language :: Python :: 3.10
Classifier: Programming Language :: Python :: 3.11
Classifier: Programming Language :: Python :: 3.12
Classifier: Programming Language :: Python :: 3.13
Classifier: Topic :: Software Development :: Libraries :: Python Modules
Classifier: Topic :: Communications :: Conferencing
Classifier: Topic :: Multimedia :: Sound/Audio
Classifier: Topic :: Multimedia :: Video
Classifier: Operating System :: POSIX :: Linux
Classifier: Operating System :: MacOS :: MacOS X
Project-URL: Homepage, https://github.com/zoom/rtms
Project-URL: Documentation, https://zoom.github.io/rtms/
Project-URL: Source, https://github.com/zoom/rtms
Project-URL: Issues, https://github.com/zoom/rtms/issues
Requires-Python: >=3.10
